importmagician/__init__.py
importmagician/import_from.py
importmagician-0.1.0.dist-info/LICENSE
importmagician-0.1.0.dist-info/METADATA
importmagician-0.1.0.dist-info/WHEEL
importmagician-0.1.0.dist-info/top_level.txt
importmagician-0.1.0.dist-info/RECORD
