Metadata-Version: 2.1
Name: importmagician
Version: 0.1.0
Summary: Voldemort's Python import helper.
Home-page: https://github.com/voldemortX/import_magician
Author: Zhengyang Feng
Author-email: zyfeng97@outlook.com
License: UNKNOWN
Platform: UNKNOWN
Classifier: Programming Language :: Python :: 3
Classifier: License :: OSI Approved :: MIT License
Classifier: Operating System :: OS Independent
Requires-Python: >=3.5
License-File: LICENSE
